MANIFEST.in
setup.cfg
setup.py
drf_tracking_dm.egg-info/PKG-INFO
drf_tracking_dm.egg-info/SOURCES.txt
drf_tracking_dm.egg-info/dependency_links.txt
drf_tracking_dm.egg-info/requires.txt
drf_tracking_dm.egg-info/top_level.txt
rest_framework_tracking/__init__.py
rest_framework_tracking/admin.py
rest_framework_tracking/apps.py
rest_framework_tracking/managers.py
rest_framework_tracking/mixins.py
rest_framework_tracking/models.py
rest_framework_tracking/migrations/0001_initial.py
rest_framework_tracking/migrations/0002_auto_20170118_1713.py
rest_framework_tracking/migrations/0003_add_errors.py
rest_framework_tracking/migrations/0004_add_verbose_name.py
rest_framework_tracking/migrations/0005_auto_20171219_1537.py
rest_framework_tracking/migrations/__init__.py